{
  "openapi": "3.0.0",
  "info": {
    "title": "hctv public API",
    "version": "0.0.1",
    "description": "OpenAPI specification for hackclub.tv's publicly documented API endpoints."
  },
  "servers": [
    {
      "url": "http://localhost:3000/api",
      "description": "Local development server"
    },
    {
      "url": "https://hctv.srizan.dev/api",
      "description": "Production server"
    }
  ],
  "components": {
    "securitySchemes": {
      "auth_session": {
        "type": "apiKey",
        "in": "cookie",
        "name": "auth_session"
      }
    }
  },
  "defaultResponseSet": "common",
  "apiDir": "./src/app/(ui)/(protected)/api",
  "schemaDir": "./src",
  "docsUrl": "api-docs",
  "ui": "scalar",
  "outputFile": "openapi.json",
  "includeOpenApiRoutes": false,
  "debug": false
}
